odoo/addons/stock_picking_responsible/README.rst
odoo/addons/stock_picking_responsible/__init__.py
odoo/addons/stock_picking_responsible/__manifest__.py
odoo/addons/stock_picking_responsible/i18n/fr_BE.po
odoo/addons/stock_picking_responsible/i18n/stock_picking_responsible.pot
odoo/addons/stock_picking_responsible/migrations/12.0.1.0.1/post-migration.py
odoo/addons/stock_picking_responsible/migrations/12.0.1.0.1/pre-migration.py
odoo/addons/stock_picking_responsible/models/__init__.py
odoo/addons/stock_picking_responsible/models/stock_picking.py
odoo/addons/stock_picking_responsible/readme/CONTRIBUTORS.rst
odoo/addons/stock_picking_responsible/readme/DESCRIPTION.rst
odoo/addons/stock_picking_responsible/static/description/icon.png
odoo/addons/stock_picking_responsible/static/description/index.html
odoo/addons/stock_picking_responsible/tests/__init__.py
odoo/addons/stock_picking_responsible/tests/test_picking_responsible.py
odoo/addons/stock_picking_responsible/views/stock_picking.xml
odoo12_addon_stock_picking_responsible-12.0.1.0.1.99.dev5.dist-info/METADATA
odoo12_addon_stock_picking_responsible-12.0.1.0.1.99.dev5.dist-info/WHEEL
odoo12_addon_stock_picking_responsible-12.0.1.0.1.99.dev5.dist-info/top_level.txt
odoo12_addon_stock_picking_responsible-12.0.1.0.1.99.dev5.dist-info/RECORD
