Metadata-Version: 2.1
Name: odoo12-addon-stock-picking-responsible
Version: 12.0.1.0.1.99.dev5
Summary: Adds a responsible partner to the picking and subscribe them to notifications.
Home-page: https://github.com/OCA/stock-logistics-workflow
Author: Coop IT Easy SC, BEES coop SC, Odoo Community Association (OCA)
Author-email: support@odoo-community.org
License: AGPL-3
Platform: UNKNOWN
Classifier: Programming Language :: Python
Classifier: Framework :: Odoo
Classifier: Framework :: Odoo :: 12.0
Classifier: License :: OSI Approved :: GNU Affero General Public License v3
Requires-Python: >=3.5
Requires-Dist: odoo <12.1dev,>=12.0a
